alibabacloud_dytnsapi20230101/__init__.py
alibabacloud_dytnsapi20230101/client.py
alibabacloud_dytnsapi20230101/models.py
alibabacloud_dytnsapi20230101_py2-1.0.2.dist-info/LICENSE
alibabacloud_dytnsapi20230101_py2-1.0.2.dist-info/METADATA
alibabacloud_dytnsapi20230101_py2-1.0.2.dist-info/WHEEL
alibabacloud_dytnsapi20230101_py2-1.0.2.dist-info/top_level.txt
alibabacloud_dytnsapi20230101_py2-1.0.2.dist-info/RECORD
